<?xml version="1.0" encoding="utf-8"?>
<!-- This is a CI serialization file for /Home/Carousel-Item-3 -->
<cms.node>
  <NodeACLID>
    <GUID>0072d163-58b7-495f-bbcd-1f15eaadf7e3</GUID>
    <ObjectType>cms.acl</ObjectType>
    <Site>
      <CodeName>LittleFashion_Kentico13</CodeName>
      <GUID>8abdfae1-d106-4e33-ab2a-d090ed0ee763</GUID>
      <ObjectType>cms.site</ObjectType>
    </Site>
  </NodeACLID>
  <NodeAlias>Carousel-Item-3</NodeAlias>
  <NodeClassID>
    <CodeName>LittleFashion_Kentico13.CarouselItem</CodeName>
    <GUID>7a1518dc-7ea2-4674-9f54-812ace5d6671</GUID>
    <ObjectType>cms.documenttype</ObjectType>
  </NodeClassID>
  <NodeGUID>41b6756c-95f4-4430-94c8-0be56bc746e9</NodeGUID>
  <NodeIsACLOwner>False</NodeIsACLOwner>
  <NodeName>Carousel Item 3</NodeName>
  <NodeOrder>3</NodeOrder>
  <NodeOwner>
    <CodeName>administrator</CodeName>
    <GUID>6415b8ce-8072-4bcd-8e48-9d7178b826b7</GUID>
    <ObjectType>cms.user</ObjectType>
  </NodeOwner>
  <NodeParentID>
    <CodeName>/Home</CodeName>
    <GUID>c8135f88-a5e8-4c6f-a2fa-a4357101127f</GUID>
    <ObjectType>cms.node</ObjectType>
    <Site>
      <CodeName>LittleFashion_Kentico13</CodeName>
      <GUID>8abdfae1-d106-4e33-ab2a-d090ed0ee763</GUID>
      <ObjectType>cms.site</ObjectType>
    </Site>
  </NodeParentID>
  <NodeSiteID>
    <CodeName>LittleFashion_Kentico13</CodeName>
    <GUID>8abdfae1-d106-4e33-ab2a-d090ed0ee763</GUID>
    <ObjectType>cms.site</ObjectType>
  </NodeSiteID>
</cms.node>