<?xml version="1.0" encoding="utf-8"?>
<cms.uielement>
  <ElementCheckModuleReadPermission>True</ElementCheckModuleReadPermission>
  <ElementDisplayName>{$administration-system.files.mediaprotection$}</ElementDisplayName>
  <ElementFromVersion>13.0</ElementFromVersion>
  <ElementGUID>395792b7-273e-4606-aea2-83ea42cbdb62</ElementGUID>
  <ElementIconClass />
  <ElementIsCustom>False</ElementIsCustom>
  <ElementIsGlobalApplication>False</ElementIsGlobalApplication>
  <ElementIsMenu>False</ElementIsMenu>
  <ElementName>Files.MediaProtection</ElementName>
  <ElementOrder>6</ElementOrder>
  <ElementParentID>
    <CodeName>System.Files</CodeName>
    <GUID>22d81413-8401-47e5-953b-adc993b5bb70</GUID>
    <ObjectType>cms.uielement</ObjectType>
    <Parent>
      <CodeName>CMS</CodeName>
      <GUID>ce1a65a0-80dc-4c53-b0e7-bdecf0aa8c02</GUID>
      <ObjectType>cms.resource</ObjectType>
    </Parent>
  </ElementParentID>
  <ElementProperties>
    <Data>
      <DisplayBreadcrumbs>False</DisplayBreadcrumbs>
    </Data>
  </ElementProperties>
  <ElementRequiresGlobalAdminPriviligeLevel>False</ElementRequiresGlobalAdminPriviligeLevel>
  <ElementResourceID>
    <CodeName>CMS</CodeName>
    <GUID>ce1a65a0-80dc-4c53-b0e7-bdecf0aa8c02</GUID>
    <ObjectType>cms.resource</ObjectType>
  </ElementResourceID>
  <ElementSize>0</ElementSize>
  <ElementTargetURL>
    <![CDATA[~/CMSModules/System/Files/System_MediaProtection.aspx]]>
  </ElementTargetURL>
  <ElementType>Url</ElementType>
</cms.uielement>